omesh/__init__.py
omesh/log.py
omesh/main.py
omesh/mesh_generation.py
open_mesh_recon-0.0.1.0.dist-info/licenses/LICENSE
open_mesh_recon-0.0.1.0.dist-info/METADATA
open_mesh_recon-0.0.1.0.dist-info/WHEEL
open_mesh_recon-0.0.1.0.dist-info/top_level.txt
open_mesh_recon-0.0.1.0.dist-info/RECORD
