Metadata-Version: 2.4
Name: open_mesh_recon
Version: 0.0.1.0
Summary: The OpenMesh package version 0.0.1 a first version of this package have the ability to work with 3D resconstruction models. Its not completed yet. wait for it.
Author-email: Mohammad Taha <mtaha13901211@gmail.com>
License: MIT
Requires-Python: >=3.8
License-File: LICENSE
Dynamic: license-file
